CHANGELOG.txt
MANIFEST.in
README.txt
setup.py
osc/__init__.py
osc.recipe.sysegg.egg-info/PKG-INFO
osc.recipe.sysegg.egg-info/SOURCES.txt
osc.recipe.sysegg.egg-info/dependency_links.txt
osc.recipe.sysegg.egg-info/entry_points.txt
osc.recipe.sysegg.egg-info/namespace_packages.txt
osc.recipe.sysegg.egg-info/not-zip-safe
osc.recipe.sysegg.egg-info/requires.txt
osc.recipe.sysegg.egg-info/top_level.txt
osc/recipe/__init__.py
osc/recipe/sysegg/__init__.py