Metadata-Version: 1.0
Name: osc.recipe.sysegg
Version: 0.1.2
Summary: zc buildout recipe to reuse eggs from python site-packages.
Home-page: UNKNOWN
Author: Oliver Tonnhofer
Author-email: olt@omniscale.de
License: MIT License
Platform: UNKNOWN
Classifier: License :: OSI Approved :: MIT License
Classifier: Framework :: Buildout
Classifier: Programming Language :: Python
